opentelemetry/instrumentation/qdrant/__init__.py
opentelemetry/instrumentation/qdrant/async_qdrant_client_methods.json
opentelemetry/instrumentation/qdrant/config.py
opentelemetry/instrumentation/qdrant/qdrant_client_methods.json
opentelemetry/instrumentation/qdrant/utils.py
opentelemetry/instrumentation/qdrant/version.py
opentelemetry/instrumentation/qdrant/wrapper.py
opentelemetry_instrumentation_qdrant-0.51.1.dist-info/METADATA
opentelemetry_instrumentation_qdrant-0.51.1.dist-info/WHEEL
opentelemetry_instrumentation_qdrant-0.51.1.dist-info/entry_points.txt
opentelemetry_instrumentation_qdrant-0.51.1.dist-info/RECORD
